Workbook

Sheet Summary
A1: Portal Performance QA — Audit Summary
A3: Audit date
A4: Auditor
A5: Build/commit
A6: Device + viewport | C6: run mobile ≤430px AND desktop ≥1280px
A7: Network profile | C7: run fast AND throttled
A9: Legend
A10: Yellow cells with blue text = your inputs (Actual ms, manual PASS/FAIL dropdowns, bug notes).
A11: Pass/Fail auto-computes wherever Max is numeric: PASS when Actual <= Max. Record the WORST of 3 tries.
A12: Qualitative rows (Max shown as —) use the PASS/FAIL dropdown; Sync functional checks use YES/NO.
A13: Example row format: Action 'Send button reacts', Max 100, Actual 87 → PASS (auto). Actual 240 → FAIL, red.
A14: Targets from docs/PERFORMANCE_QA_CHECKLIST.md; base layer is Core Web Vitals (LCP 2.5s, INP 200ms, CLS 0.1).
A16: Run summary (fail counts update live from each tab)
A17: Tab | B17: Rows measured | C17: Fails | D17: Verdict
A18: Chat | B18: =COUNTIF(Chat!F:F,"PASS")+COUNTIF(Chat!F:F,"FAIL")+COUNTIF(Chat!F:F,"YES")+COUNTIF(Chat!F:F,"NO") -> 0 | C18: =COUNTIF(Chat!F:F,"FAIL")+COUNTIF(Chat!F:F,"NO") -> 0 | D18: =IF(B18=0,"",IF(C18=0,"PASS","FAIL"))
A19: Dashboard | B19: =COUNTIF(Dashboard!F:F,"PASS")+COUNTIF(Dashboard!F:F,"FAIL")+COUNTIF(Dashboard!F:F,"YES")+COUNTIF(Dashboard!F:F,"NO") -> 0 | C19: =COUNTIF(Dashboard!F:F,"FAIL")+COUNTIF(Dashboard!F:F,"NO") -> 0 | D19: =IF(B19=0,"",IF(C19=0,"PASS","FAIL"))
A20: Trackers | B20: =COUNTIF(Trackers!F:F,"PASS")+COUNTIF(Trackers!F:F,"FAIL")+COUNTIF(Trackers!F:F,"YES")+COUNTIF(Trackers!F:F,"NO") -> 0 | C20: =COUNTIF(Trackers!F:F,"FAIL")+COUNTIF(Trackers!F:F,"NO") -> 0 | D20: =IF(B20=0,"",IF(C20=0,"PASS","FAIL"))
A21: Assets | B21: =COUNTIF(Assets!F:F,"PASS")+COUNTIF(Assets!F:F,"FAIL")+COUNTIF(Assets!F:F,"YES")+COUNTIF(Assets!F:F,"NO") -> 0 | C21: =COUNTIF(Assets!F:F,"FAIL")+COUNTIF(Assets!F:F,"NO") -> 0 | D21: =IF(B21=0,"",IF(C21=0,"PASS","FAIL"))
A22: Liabilities | B22: =COUNTIF(Liabilities!F:F,"PASS")+COUNTIF(Liabilities!F:F,"FAIL")+COUNTIF(Liabilities!F:F,"YES")+COUNTIF(Liabilities!F:F,"NO") -> 0 | C22: =COUNTIF(Liabilities!F:F,"FAIL")+COUNTIF(Liabilities!F:F,"NO") -> 0 | D22: =IF(B22=0,"",IF(C22=0,"PASS","FAIL"))
A23: Info Profiles | B23: =COUNTIF('Info Profiles'!F:F,"PASS")+COUNTIF('Info Profiles'!F:F,"FAIL")+COUNTIF('Info Profiles'!F:F,"YES")+COUNTIF('Info Profiles'!F:F,"NO") -> 0 | C23: =COUNTIF('Info Profiles'!F:F,"FAIL")+COUNTIF('Info Profiles'!F:F,"NO") -> 0 | D23: =IF(B23=0,"",IF(C23=0,"PASS","FAIL"))
A24: Profile Detail | B24: =COUNTIF('Profile Detail'!F:F,"PASS")+COUNTIF('Profile Detail'!F:F,"FAIL")+COUNTIF('Profile Detail'!F:F,"YES")+COUNTIF('Profile Detail'!F:F,"NO") -> 0 | C24: =COUNTIF('Profile Detail'!F:F,"FAIL")+COUNTIF('Profile Detail'!F:F,"NO") -> 0 | D24: =IF(B24=0,"",IF(C24=0,"PASS","FAIL"))
A25: Calendar | B25: =COUNTIF(Calendar!F:F,"PASS")+COUNTIF(Calendar!F:F,"FAIL")+COUNTIF(Calendar!F:F,"YES")+COUNTIF(Calendar!F:F,"NO") -> 0 | C25: =COUNTIF(Calendar!F:F,"FAIL")+COUNTIF(Calendar!F:F,"NO") -> 0 | D25: =IF(B25=0,"",IF(C25=0,"PASS","FAIL"))
A26: Tasks | B26: =COUNTIF(Tasks!F:F,"PASS")+COUNTIF(Tasks!F:F,"FAIL")+COUNTIF(Tasks!F:F,"YES")+COUNTIF(Tasks!F:F,"NO") -> 0 | C26: =COUNTIF(Tasks!F:F,"FAIL")+COUNTIF(Tasks!F:F,"NO") -> 0 | D26: =IF(B26=0,"",IF(C26=0,"PASS","FAIL"))
A27: Finance | B27: =COUNTIF(Finance!F:F,"PASS")+COUNTIF(Finance!F:F,"FAIL")+COUNTIF(Finance!F:F,"YES")+COUNTIF(Finance!F:F,"NO") -> 0 | C27: =COUNTIF(Finance!F:F,"FAIL")+COUNTIF(Finance!F:F,"NO") -> 0 | D27: =IF(B27=0,"",IF(C27=0,"PASS","FAIL"))
A28: Habits | B28: =COUNTIF(Habits!F:F,"PASS")+COUNTIF(Habits!F:F,"FAIL")+COUNTIF(Habits!F:F,"YES")+COUNTIF(Habits!F:F,"NO") -> 0 | C28: =COUNTIF(Habits!F:F,"FAIL")+COUNTIF(Habits!F:F,"NO") -> 0 | D28: =IF(B28=0,"",IF(C28=0,"PASS","FAIL"))
A29: Journal | B29: =COUNTIF(Journal!F:F,"PASS")+COUNTIF(Journal!F:F,"FAIL")+COUNTIF(Journal!F:F,"YES")+COUNTIF(Journal!F:F,"NO") -> 0 | C29: =COUNTIF(Journal!F:F,"FAIL")+COUNTIF(Journal!F:F,"NO") -> 0 | D29: =IF(B29=0,"",IF(C29=0,"PASS","FAIL"))
A30: Obligations | B30: =COUNTIF(Obligations!F:F,"PASS")+COUNTIF(Obligations!F:F,"FAIL")+COUNTIF(Obligations!F:F,"YES")+COUNTIF(Obligations!F:F,"NO") -> 0 | C30: =COUNTIF(Obligations!F:F,"FAIL")+COUNTIF(Obligations!F:F,"NO") -> 0 | D30: =IF(B30=0,"",IF(C30=0,"PASS","FAIL"))
A31: Goals | B31: =COUNTIF(Goals!F:F,"PASS")+COUNTIF(Goals!F:F,"FAIL")+COUNTIF(Goals!F:F,"YES")+COUNTIF(Goals!F:F,"NO") -> 0 | C31: =COUNTIF(Goals!F:F,"FAIL")+COUNTIF(Goals!F:F,"NO") -> 0 | D31: =IF(B31=0,"",IF(C31=0,"PASS","FAIL"))
A32: Wellness | B32: =COUNTIF(Wellness!F:F,"PASS")+COUNTIF(Wellness!F:F,"FAIL")+COUNTIF(Wellness!F:F,"YES")+COUNTIF(Wellness!F:F,"NO") -> 0 | C32: =COUNTIF(Wellness!F:F,"FAIL")+COUNTIF(Wellness!F:F,"NO") -> 0 | D32: =IF(B32=0,"",IF(C32=0,"PASS","FAIL"))
A33: Insights | B33: =COUNTIF(Insights!F:F,"PASS")+COUNTIF(Insights!F:F,"FAIL")+COUNTIF(Insights!F:F,"YES")+COUNTIF(Insights!F:F,"NO") -> 0 | C33: =COUNTIF(Insights!F:F,"FAIL")+COUNTIF(Insights!F:F,"NO") -> 0 | D33: =IF(B33=0,"",IF(C33=0,"PASS","FAIL"))
A34: Artifacts | B34: =COUNTIF(Artifacts!F:F,"PASS")+COUNTIF(Artifacts!F:F,"FAIL")+COUNTIF(Artifacts!F:F,"YES")+COUNTIF(Artifacts!F:F,"NO") -> 0 | C34: =COUNTIF(Artifacts!F:F,"FAIL")+COUNTIF(Artifacts!F:F,"NO") -> 0 | D34: =IF(B34=0,"",IF(C34=0,"PASS","FAIL"))
A35: Editor | B35: =COUNTIF(Editor!F:F,"PASS")+COUNTIF(Editor!F:F,"FAIL")+COUNTIF(Editor!F:F,"YES")+COUNTIF(Editor!F:F,"NO") -> 0 | C35: =COUNTIF(Editor!F:F,"FAIL")+COUNTIF(Editor!F:F,"NO") -> 0 | D35: =IF(B35=0,"",IF(C35=0,"PASS","FAIL"))
A36: Settings | B36: =COUNTIF(Settings!F:F,"PASS")+COUNTIF(Settings!F:F,"FAIL")+COUNTIF(Settings!F:F,"YES")+COUNTIF(Settings!F:F,"NO") -> 0 | C36: =COUNTIF(Settings!F:F,"FAIL")+COUNTIF(Settings!F:F,"NO") -> 0 | D36: =IF(B36=0,"",IF(C36=0,"PASS","FAIL"))
A37: CRUD | B37: =COUNTIF(CRUD!F:F,"PASS")+COUNTIF(CRUD!F:F,"FAIL")+COUNTIF(CRUD!F:F,"YES")+COUNTIF(CRUD!F:F,"NO") -> 0 | C37: =COUNTIF(CRUD!F:F,"FAIL")+COUNTIF(CRUD!F:F,"NO") -> 0 | D37: =IF(B37=0,"",IF(C37=0,"PASS","FAIL"))
A38: Chat Diagnostic | B38: =COUNTIF('Chat Diagnostic'!F:F,"PASS")+COUNTIF('Chat Diagnostic'!F:F,"FAIL")+COUNTIF('Chat Diagnostic'!F:F,"YES")+COUNTIF('Chat Diagnostic'!F:F,"NO") -> 0 | C38: =COUNTIF('Chat Diagnostic'!F:F,"FAIL")+COUNTIF('Chat Diagnostic'!F:F,"NO") -> 0 | D38: =IF(B38=0,"",IF(C38=0,"PASS","FAIL"))
A39: Navigation | B39: =COUNTIF(Navigation!F:F,"PASS")+COUNTIF(Navigation!F:F,"FAIL")+COUNTIF(Navigation!F:F,"YES")+COUNTIF(Navigation!F:F,"NO") -> 0 | C39: =COUNTIF(Navigation!F:F,"FAIL")+COUNTIF(Navigation!F:F,"NO") -> 0 | D39: =IF(B39=0,"",IF(C39=0,"PASS","FAIL"))
A40: Micro | B40: =COUNTIF(Micro!E:E,"PASS")+COUNTIF(Micro!E:E,"FAIL")+COUNTIF(Micro!E:E,"YES")+COUNTIF(Micro!E:E,"NO") -> 0 | C40: =COUNTIF(Micro!E:E,"FAIL")+COUNTIF(Micro!E:E,"NO") -> 0 | D40: =IF(B40=0,"",IF(C40=0,"PASS","FAIL"))
A41: Sync | B41: =COUNTIF(Sync!F:F,"PASS")+COUNTIF(Sync!F:F,"FAIL")+COUNTIF(Sync!F:F,"YES")+COUNTIF(Sync!F:F,"NO") -> 0 | C41: =COUNTIF(Sync!F:F,"FAIL")+COUNTIF(Sync!F:F,"NO") -> 0 | D41: =IF(B41=0,"",IF(C41=0,"PASS","FAIL"))
A42: TOTAL | B42: =SUM(B18:B41) -> 0 | C42: =SUM(C18:C41) -> 0 | D42: =IF(B42=0,"",IF(C42=0,"PASS","FAIL"))
A44: Severity rules
A45: Severity | B45: Definition | C45: Examples
A46: P0 | B46: Data integrity broken | C46: Saved wrong, cross-profile leakage, delete fails, duplicates, wrong totals, wrong calendar writes
A47: P1 | B47: Mutation succeeds but user can't see it | C47: UI not updating, stale routes, chat item in wrong place, modal hangs >500ms
A48: P2 | B48: Noticeable non-blocking lag | C48: Animation hitch, delayed badge, dropdown >200ms
A49: P3 | B49: Cosmetic micro-jank | C49: No data or usability impact
A51: Release gate: zero open P0/P1; every FAIL row has a filed bug with repro. Overall verdict is computed in D42.

Sheet Chat
A1: Route audit — Chat (/)
A2: Worst of 3 tries. Yellow cells are inputs. Pass/Fail auto-computes where Max is numeric; qualitative rows use the PASS/FAIL dropdown.
A4: # | B4: Action | C4: Ideal (ms) | D4: Max (ms) | E4: Actual | F4: Pass/Fail | G4: Bug notes
A5: R1 | B5: Shell/skeleton visible after nav click | C5: 100 | D5: 300 | F5: =IF(E5="","",IF(E5<=D5,"PASS","FAIL"))
A6: R2 | B6: First usable content (LCP) | C6: 2000 | D6: 2500 | F6: =IF(E6="","",IF(E6<=D6,"PASS","FAIL"))
A7: R3 | B7: Data settled enough to use (1500 max allowed on heavy screens: Dashboard, Finance, Insights) | C7: 1000 | D7: 1500 | F7: =IF(E7="","",IF(E7<=D7,"PASS","FAIL"))
A8: R4 | B8: Every sub-tab: content swap | C8: 150 | D8: 250 | F8: =IF(E8="","",IF(E8<=D8,"PASS","FAIL"))
A9: R5 | B9: Every modal/sheet on this route: open | C9: 150 | D9: 250 | F9: =IF(E9="","",IF(E9<=D9,"PASS","FAIL"))
A10: R6 | B10: Every modal/sheet: close (X and Escape) | C10: 100 | D10: 200 | F10: =IF(E10="","",IF(E10<=D10,"PASS","FAIL"))
A11: R7 | B11: Every dropdown/menu/date-picker: open + selection applies | C11: 100 | D11: 200 | F11: =IF(E11="","",IF(E11<=D11,"PASS","FAIL"))
A12: R8 | B12: Search/filter input on this route: per-keystroke | C12: 50 | D12: 100 | F12: =IF(E12="","",IF(E12<=D12,"PASS","FAIL"))
A13: R9 | B13: Navigate away and back: no stale flash, state preserved | D13: —
A14: R10 | B14: Repeat primary action 5x fast: no jank, no dupes, no races | D14: —
A15: R11 | B15: CLS during load and after mutations (enter CLS value, not ms; max 0.1) | D15: 0.1 | F15: =IF(E15="","",IF(E15<=D15,"PASS","FAIL"))
A16: R12 | B16: Mobile-width rerun of R1–R11 all within limits | D16: —

Sheet Dashboard
A1: Route audit — Dashboard (/dashboard)
A2: Worst of 3 tries. Yellow cells are inputs. Pass/Fail auto-computes where Max is numeric; qualitative rows use the PASS/FAIL dropdown.
A4: # | B4: Action | C4: Ideal (ms) | D4: Max (ms) | E4: Actual | F4: Pass/Fail | G4: Bug notes
A5: R1 | B5: Shell/skeleton visible after nav click | C5: 100 | D5: 300 | F5: =IF(E5="","",IF(E5<=D5,"PASS","FAIL"))
A6: R2 | B6: First usable content (LCP) | C6: 2000 | D6: 2500 | F6: =IF(E6="","",IF(E6<=D6,"PASS","FAIL"))
A7: R3 | B7: Data settled enough to use (1500 max allowed on heavy screens: Dashboard, Finance, Insights) | C7: 1000 | D7: 1500 | F7: =IF(E7="","",IF(E7<=D7,"PASS","FAIL"))
A8: R4 | B8: Every sub-tab: content swap | C8: 150 | D8: 250 | F8: =IF(E8="","",IF(E8<=D8,"PASS","FAIL"))
A9: R5 | B9: Every modal/sheet on this route: open | C9: 150 | D9: 250 | F9: =IF(E9="","",IF(E9<=D9,"PASS","FAIL"))
A10: R6 | B10: Every modal/sheet: close (X and Escape) | C10: 100 | D10: 200 | F10: =IF(E10="","",IF(E10<=D10,"PASS","FAIL"))
A11: R7 | B11: Every dropdown/menu/date-picker: open + selection applies | C11: 100 | D11: 200 | F11: =IF(E11="","",IF(E11<=D11,"PASS","FAIL"))
A12: R8 | B12: Search/filter input on this route: per-keystroke | C12: 50 | D12: 100 | F12: =IF(E12="","",IF(E12<=D12,"PASS","FAIL"))
A13: R9 | B13: Navigate away and back: no stale flash, state preserved | D13: —
A14: R10 | B14: Repeat primary action 5x fast: no jank, no dupes, no races | D14: —
A15: R11 | B15: CLS during load and after mutations (enter CLS value, not ms; max 0.1) | D15: 0.1 | F15: =IF(E15="","",IF(E15<=D15,"PASS","FAIL"))
A16: R12 | B16: Mobile-width rerun of R1–R11 all within limits | D16: —

Sheet Trackers
A1: Route audit — Trackers (/trackers)
A2: Worst of 3 tries. Yellow cells are inputs. Pass/Fail auto-computes where Max is numeric; qualitative rows use the PASS/FAIL dropdown.
A4: # | B4: Action | C4: Ideal (ms) | D4: Max (ms) | E4: Actual | F4: Pass/Fail | G4: Bug notes
A5: R1 | B5: Shell/skeleton visible after nav click | C5: 100 | D5: 300 | F5: =IF(E5="","",IF(E5<=D5,"PASS","FAIL"))
A6: R2 | B6: First usable content (LCP) | C6: 2000 | D6: 2500 | F6: =IF(E6="","",IF(E6<=D6,"PASS","FAIL"))
A7: R3 | B7: Data settled enough to use (1500 max allowed on heavy screens: Dashboard, Finance, Insights) | C7: 1000 | D7: 1500 | F7: =IF(E7="","",IF(E7<=D7,"PASS","FAIL"))
A8: R4 | B8: Every sub-tab: content swap | C8: 150 | D8: 250 | F8: =IF(E8="","",IF(E8<=D8,"PASS","FAIL"))
A9: R5 | B9: Every modal/sheet on this route: open | C9: 150 | D9: 250 | F9: =IF(E9="","",IF(E9<=D9,"PASS","FAIL"))
A10: R6 | B10: Every modal/sheet: close (X and Escape) | C10: 100 | D10: 200 | F10: =IF(E10="","",IF(E10<=D10,"PASS","FAIL"))
A11: R7 | B11: Every dropdown/menu/date-picker: open + selection applies | C11: 100 | D11: 200 | F11: =IF(E11="","",IF(E11<=D11,"PASS","FAIL"))
A12: R8 | B12: Search/filter input on this route: per-keystroke | C12: 50 | D12: 100 | F12: =IF(E12="","",IF(E12<=D12,"PASS","FAIL"))
A13: R9 | B13: Navigate away and back: no stale flash, state preserved | D13: —
A14: R10 | B14: Repeat primary action 5x fast: no jank, no dupes, no races | D14: —
A15: R11 | B15: CLS during load and after mutations (enter CLS value, not ms; max 0.1) | D15: 0.1 | F15: =IF(E15="","",IF(E15<=D15,"PASS","FAIL"))
A16: R12 | B16: Mobile-width rerun of R1–R11 all within limits | D16: —

Sheet Assets
A1: Route audit — Assets (/linked)
A2: Worst of 3 tries. Yellow cells are inputs. Pass/Fail auto-computes where Max is numeric; qualitative rows use the PASS/FAIL dropdown.
A4: # | B4: Action | C4: Ideal (ms) | D4: Max (ms) | E4: Actual | F4: Pass/Fail | G4: Bug notes
A5: R1 | B5: Shell/skeleton visible after nav click | C5: 100 | D5: 300 | F5: =IF(E5="","",IF(E5<=D5,"PASS","FAIL"))
A6: R2 | B6: First usable content (LCP) | C6: 2000 | D6: 2500 | F6: =IF(E6="","",IF(E6<=D6,"PASS","FAIL"))
A7: R3 | B7: Data settled enough to use (1500 max allowed on heavy screens: Dashboard, Finance, Insights) | C7: 1000 | D7: 1500 | F7: =IF(E7="","",IF(E7<=D7,"PASS","FAIL"))
A8: R4 | B8: Every sub-tab: content swap | C8: 150 | D8: 250 | F8: =IF(E8="","",IF(E8<=D8,"PASS","FAIL"))
A9: R5 | B9: Every modal/sheet on this route: open | C9: 150 | D9: 250 | F9: =IF(E9="","",IF(E9<=D9,"PASS","FAIL"))
A10: R6 | B10: Every modal/sheet: close (X and Escape) | C10: 100 | D10: 200 | F10: =IF(E10="","",IF(E10<=D10,"PASS","FAIL"))
A11: R7 | B11: Every dropdown/menu/date-picker: open + selection applies | C11: 100 | D11: 200 | F11: =IF(E11="","",IF(E11<=D11,"PASS","FAIL"))
A12: R8 | B12: Search/filter input on this route: per-keystroke | C12: 50 | D12: 100 | F12: =IF(E12="","",IF(E12<=D12,"PASS","FAIL"))
A13: R9 | B13: Navigate away and back: no stale flash, state preserved | D13: —
A14: R10 | B14: Repeat primary action 5x fast: no jank, no dupes, no races | D14: —
A15: R11 | B15: CLS during load and after mutations (enter CLS value, not ms; max 0.1) | D15: 0.1 | F15: =IF(E15="","",IF(E15<=D15,"PASS","FAIL"))
A16: R12 | B16: Mobile-width rerun of R1–R11 all within limits | D16: —

Sheet Liabilities
A1: Route audit — Liabilities (/liabilities)
A2: Worst of 3 tries. Yellow cells are inputs. Pass/Fail auto-computes where Max is numeric; qualitative rows use the PASS/FAIL dropdown.
A4: # | B4: Action | C4: Ideal (ms) | D4: Max (ms) | E4: Actual | F4: Pass/Fail | G4: Bug notes
A5: R1 | B5: Shell/skeleton visible after nav click | C5: 100 | D5: 300 | F5: =IF(E5="","",IF(E5<=D5,"PASS","FAIL"))
A6: R2 | B6: First usable content (LCP) | C6: 2000 | D6: 2500 | F6: =IF(E6="","",IF(E6<=D6,"PASS","FAIL"))
A7: R3 | B7: Data settled enough to use (1500 max allowed on heavy screens: Dashboard, Finance, Insights) | C7: 1000 | D7: 1500 | F7: =IF(E7="","",IF(E7<=D7,"PASS","FAIL"))
A8: R4 | B8: Every sub-tab: content swap | C8: 150 | D8: 250 | F8: =IF(E8="","",IF(E8<=D8,"PASS","FAIL"))
A9: R5 | B9: Every modal/sheet on this route: open | C9: 150 | D9: 250 | F9: =IF(E9="","",IF(E9<=D9,"PASS","FAIL"))
A10: R6 | B10: Every modal/sheet: close (X and Escape) | C10: 100 | D10: 200 | F10: =IF(E10="","",IF(E10<=D10,"PASS","FAIL"))
A11: R7 | B11: Every dropdown/menu/date-picker: open + selection applies | C11: 100 | D11: 200 | F11: =IF(E11="","",IF(E11<=D11,"PASS","FAIL"))
A12: R8 | B12: Search/filter input on this route: per-keystroke | C12: 50 | D12: 100 | F12: =IF(E12="","",IF(E12<=D12,"PASS","FAIL"))
A13: R9 | B13: Navigate away and back: no stale flash, state preserved | D13: —
A14: R10 | B14: Repeat primary action 5x fast: no jank, no dupes, no races | D14: —
A15: R11 | B15: CLS during load and after mutations (enter CLS value, not ms; max 0.1) | D15: 0.1 | F15: =IF(E15="","",IF(E15<=D15,"PASS","FAIL"))
A16: R12 | B16: Mobile-width rerun of R1–R11 all within limits | D16: —

Sheet Info Profiles
A1: Route audit — Info / Profiles (/profiles, /profiles/:id/info)
A2: Worst of 3 tries. Yellow cells are inputs. Pass/Fail auto-computes where Max is numeric; qualitative rows use the PASS/FAIL dropdown.
A4: # | B4: Action | C4: Ideal (ms) | D4: Max (ms) | E4: Actual | F4: Pass/Fail | G4: Bug notes
A5: R1 | B5: Shell/skeleton visible after nav click | C5: 100 | D5: 300 | F5: =IF(E5="","",IF(E5<=D5,"PASS","FAIL"))
A6: R2 | B6: First usable content (LCP) | C6: 2000 | D6: 2500 | F6: =IF(E6="","",IF(E6<=D6,"PASS","FAIL"))
A7: R3 | B7: Data settled enough to use (1500 max allowed on heavy screens: Dashboard, Finance, Insights) | C7: 1000 | D7: 1500 | F7: =IF(E7="","",IF(E7<=D7,"PASS","FAIL"))
A8: R4 | B8: Every sub-tab: content swap | C8: 150 | D8: 250 | F8: =IF(E8="","",IF(E8<=D8,"PASS","FAIL"))
A9: R5 | B9: Every modal/sheet on this route: open | C9: 150 | D9: 250 | F9: =IF(E9="","",IF(E9<=D9,"PASS","FAIL"))
A10: R6 | B10: Every modal/sheet: close (X and Escape) | C10: 100 | D10: 200 | F10: =IF(E10="","",IF(E10<=D10,"PASS","FAIL"))
A11: R7 | B11: Every dropdown/menu/date-picker: open + selection applies | C11: 100 | D11: 200 | F11: =IF(E11="","",IF(E11<=D11,"PASS","FAIL"))
A12: R8 | B12: Search/filter input on this route: per-keystroke | C12: 50 | D12: 100 | F12: =IF(E12="","",IF(E12<=D12,"PASS","FAIL"))
A13: R9 | B13: Navigate away and back: no stale flash, state preserved | D13: —
A14: R10 | B14: Repeat primary action 5x fast: no jank, no dupes, no races | D14: —
A15: R11 | B15: CLS during load and after mutations (enter CLS value, not ms; max 0.1) | D15: 0.1 | F15: =IF(E15="","",IF(E15<=D15,"PASS","FAIL"))
A16: R12 | B16: Mobile-width rerun of R1–R11 all within limits | D16: —

Sheet Profile Detail
A1: Route audit — Profile detail (/profiles/:id)
A2: Worst of 3 tries. Yellow cells are inputs. Pass/Fail auto-computes where Max is numeric; qualitative rows use the PASS/FAIL dropdown.
A4: # | B4: Action | C4: Ideal (ms) | D4: Max (ms) | E4: Actual | F4: Pass/Fail | G4: Bug notes
A5: R1 | B5: Shell/skeleton visible after nav click | C5: 100 | D5: 300 | F5: =IF(E5="","",IF(E5<=D5,"PASS","FAIL"))
A6: R2 | B6: First usable content (LCP) | C6: 2000 | D6: 2500 | F6: =IF(E6="","",IF(E6<=D6,"PASS","FAIL"))
A7: R3 | B7: Data settled enough to use (1500 max allowed on heavy screens: Dashboard, Finance, Insights) | C7: 1000 | D7: 1500 | F7: =IF(E7="","",IF(E7<=D7,"PASS","FAIL"))
A8: R4 | B8: Every sub-tab: content swap | C8: 150 | D8: 250 | F8: =IF(E8="","",IF(E8<=D8,"PASS","FAIL"))
A9: R5 | B9: Every modal/sheet on this route: open | C9: 150 | D9: 250 | F9: =IF(E9="","",IF(E9<=D9,"PASS","FAIL"))
A10: R6 | B10: Every modal/sheet: close (X and Escape) | C10: 100 | D10: 200 | F10: =IF(E10="","",IF(E10<=D10,"PASS","FAIL"))
A11: R7 | B11: Every dropdown/menu/date-picker: open + selection applies | C11: 100 | D11: 200 | F11: =IF(E11="","",IF(E11<=D11,"PASS","FAIL"))
A12: R8 | B12: Search/filter input on this route: per-keystroke | C12: 50 | D12: 100 | F12: =IF(E12="","",IF(E12<=D12,"PASS","FAIL"))
A13: R9 | B13: Navigate away and back: no stale flash, state preserved | D13: —
A14: R10 | B14: Repeat primary action 5x fast: no jank, no dupes, no races | D14: —
A15: R11 | B15: CLS during load and after mutations (enter CLS value, not ms; max 0.1) | D15: 0.1 | F15: =IF(E15="","",IF(E15<=D15,"PASS","FAIL"))
A16: R12 | B16: Mobile-width rerun of R1–R11 all within limits | D16: —

Sheet Calendar
A1: Route audit — Calendar (/calendar)
A2: Worst of 3 tries. Yellow cells are inputs. Pass/Fail auto-computes where Max is numeric; qualitative rows use the PASS/FAIL dropdown.
A4: # | B4: Action | C4: Ideal (ms) | D4: Max (ms) | E4: Actual | F4: Pass/Fail | G4: Bug notes
A5: R1 | B5: Shell/skeleton visible after nav click | C5: 100 | D5: 300 | F5: =IF(E5="","",IF(E5<=D5,"PASS","FAIL"))
A6: R2 | B6: First usable content (LCP) | C6: 2000 | D6: 2500 | F6: =IF(E6="","",IF(E6<=D6,"PASS","FAIL"))
A7: R3 | B7: Data settled enough to use (1500 max allowed on heavy screens: Dashboard, Finance, Insights) | C7: 1000 | D7: 1500 | F7: =IF(E7="","",IF(E7<=D7,"PASS","FAIL"))
A8: R4 | B8: Every sub-tab: content swap | C8: 150 | D8: 250 | F8: =IF(E8="","",IF(E8<=D8,"PASS","FAIL"))
A9: R5 | B9: Every modal/sheet on this route: open | C9: 150 | D9: 250 | F9: =IF(E9="","",IF(E9<=D9,"PASS","FAIL"))
A10: R6 | B10: Every modal/sheet: close (X and Escape) | C10: 100 | D10: 200 | F10: =IF(E10="","",IF(E10<=D10,"PASS","FAIL"))
A11: R7 | B11: Every dropdown/menu/date-picker: open + selection applies | C11: 100 | D11: 200 | F11: =IF(E11="","",IF(E11<=D11,"PASS","FAIL"))
A12: R8 | B12: Search/filter input on this route: per-keystroke | C12: 50 | D12: 100 | F12: =IF(E12="","",IF(E12<=D12,"PASS","FAIL"))
A13: R9 | B13: Navigate away and back: no stale flash, state preserved | D13: —
A14: R10 | B14: Repeat primary action 5x fast: no jank, no dupes, no races | D14: —
A15: R11 | B15: CLS during load and after mutations (enter CLS value, not ms; max 0.1) | D15: 0.1 | F15: =IF(E15="","",IF(E15<=D15,"PASS","FAIL"))
A16: R12 | B16: Mobile-width rerun of R1–R11 all within limits | D16: —

Sheet Tasks
A1: Route audit — Tasks (/tasks)
A2: Worst of 3 tries. Yellow cells are inputs. Pass/Fail auto-computes where Max is numeric; qualitative rows use the PASS/FAIL dropdown.
A4: # | B4: Action | C4: Ideal (ms) | D4: Max (ms) | E4: Actual | F4: Pass/Fail | G4: Bug notes
A5: R1 | B5: Shell/skeleton visible after nav click | C5: 100 | D5: 300 | F5: =IF(E5="","",IF(E5<=D5,"PASS","FAIL"))
A6: R2 | B6: First usable content (LCP) | C6: 2000 | D6: 2500 | F6: =IF(E6="","",IF(E6<=D6,"PASS","FAIL"))
A7: R3 | B7: Data settled enough to use (1500 max allowed on heavy screens: Dashboard, Finance, Insights) | C7: 1000 | D7: 1500 | F7: =IF(E7="","",IF(E7<=D7,"PASS","FAIL"))
A8: R4 | B8: Every sub-tab: content swap | C8: 150 | D8: 250 | F8: =IF(E8="","",IF(E8<=D8,"PASS","FAIL"))
A9: R5 | B9: Every modal/sheet on this route: open | C9: 150 | D9: 250 | F9: =IF(E9="","",IF(E9<=D9,"PASS","FAIL"))
A10: R6 | B10: Every modal/sheet: close (X and Escape) | C10: 100 | D10: 200 | F10: =IF(E10="","",IF(E10<=D10,"PASS","FAIL"))
A11: R7 | B11: Every dropdown/menu/date-picker: open + selection applies | C11: 100 | D11: 200 | F11: =IF(E11="","",IF(E11<=D11,"PASS","FAIL"))
A12: R8 | B12: Search/filter input on this route: per-keystroke | C12: 50 | D12: 100 | F12: =IF(E12="","",IF(E12<=D12,"PASS","FAIL"))
A13: R9 | B13: Navigate away and back: no stale flash, state preserved | D13: —
A14: R10 | B14: Repeat primary action 5x fast: no jank, no dupes, no races | D14: —
A15: R11 | B15: CLS during load and after mutations (enter CLS value, not ms; max 0.1) | D15: 0.1 | F15: =IF(E15="","",IF(E15<=D15,"PASS","FAIL"))
A16: R12 | B16: Mobile-width rerun of R1–R11 all within limits | D16: —

Sheet Finance
A1: Route audit — Finance (/finance)
A2: Worst of 3 tries. Yellow cells are inputs. Pass/Fail auto-computes where Max is numeric; qualitative rows use the PASS/FAIL dropdown.
A4: # | B4: Action | C4: Ideal (ms) | D4: Max (ms) | E4: Actual | F4: Pass/Fail | G4: Bug notes
A5: R1 | B5: Shell/skeleton visible after nav click | C5: 100 | D5: 300 | F5: =IF(E5="","",IF(E5<=D5,"PASS","FAIL"))
A6: R2 | B6: First usable content (LCP) | C6: 2000 | D6: 2500 | F6: =IF(E6="","",IF(E6<=D6,"PASS","FAIL"))
A7: R3 | B7: Data settled enough to use (1500 max allowed on heavy screens: Dashboard, Finance, Insights) | C7: 1000 | D7: 1500 | F7: =IF(E7="","",IF(E7<=D7,"PASS","FAIL"))
A8: R4 | B8: Every sub-tab: content swap | C8: 150 | D8: 250 | F8: =IF(E8="","",IF(E8<=D8,"PASS","FAIL"))
A9: R5 | B9: Every modal/sheet on this route: open | C9: 150 | D9: 250 | F9: =IF(E9="","",IF(E9<=D9,"PASS","FAIL"))
A10: R6 | B10: Every modal/sheet: close (X and Escape) | C10: 100 | D10: 200 | F10: =IF(E10="","",IF(E10<=D10,"PASS","FAIL"))
A11: R7 | B11: Every dropdown/menu/date-picker: open + selection applies | C11: 100 | D11: 200 | F11: =IF(E11="","",IF(E11<=D11,"PASS","FAIL"))
A12: R8 | B12: Search/filter input on this route: per-keystroke | C12: 50 | D12: 100 | F12: =IF(E12="","",IF(E12<=D12,"PASS","FAIL"))
A13: R9 | B13: Navigate away and back: no stale flash, state preserved | D13: —
A14: R10 | B14: Repeat primary action 5x fast: no jank, no dupes, no races | D14: —
A15: R11 | B15: CLS during load and after mutations (enter CLS value, not ms; max 0.1) | D15: 0.1 | F15: =IF(E15="","",IF(E15<=D15,"PASS","FAIL"))
A16: R12 | B16: Mobile-width rerun of R1–R11 all within limits | D16: —

Sheet Habits
A1: Route audit — Habits (/habits)
A2: Worst of 3 tries. Yellow cells are inputs. Pass/Fail auto-computes where Max is numeric; qualitative rows use the PASS/FAIL dropdown.
A4: # | B4: Action | C4: Ideal (ms) | D4: Max (ms) | E4: Actual | F4: Pass/Fail | G4: Bug notes
A5: R1 | B5: Shell/skeleton visible after nav click | C5: 100 | D5: 300 | F5: =IF(E5="","",IF(E5<=D5,"PASS","FAIL"))
A6: R2 | B6: First usable content (LCP) | C6: 2000 | D6: 2500 | F6: =IF(E6="","",IF(E6<=D6,"PASS","FAIL"))
A7: R3 | B7: Data settled enough to use (1500 max allowed on heavy screens: Dashboard, Finance, Insights) | C7: 1000 | D7: 1500 | F7: =IF(E7="","",IF(E7<=D7,"PASS","FAIL"))
A8: R4 | B8: Every sub-tab: content swap | C8: 150 | D8: 250 | F8: =IF(E8="","",IF(E8<=D8,"PASS","FAIL"))
A9: R5 | B9: Every modal/sheet on this route: open | C9: 150 | D9: 250 | F9: =IF(E9="","",IF(E9<=D9,"PASS","FAIL"))
A10: R6 | B10: Every modal/sheet: close (X and Escape) | C10: 100 | D10: 200 | F10: =IF(E10="","",IF(E10<=D10,"PASS","FAIL"))
A11: R7 | B11: Every dropdown/menu/date-picker: open + selection applies | C11: 100 | D11: 200 | F11: =IF(E11="","",IF(E11<=D11,"PASS","FAIL"))
A12: R8 | B12: Search/filter input on this route: per-keystroke | C12: 50 | D12: 100 | F12: =IF(E12="","",IF(E12<=D12,"PASS","FAIL"))
A13: R9 | B13: Navigate away and back: no stale flash, state preserved | D13: —
A14: R10 | B14: Repeat primary action 5x fast: no jank, no dupes, no races | D14: —
A15: R11 | B15: CLS during load and after mutations (enter CLS value, not ms; max 0.1) | D15: 0.1 | F15: =IF(E15="","",IF(E15<=D15,"PASS","FAIL"))
A16: R12 | B16: Mobile-width rerun of R1–R11 all within limits | D16: —

Sheet Journal
A1: Route audit — Journal (/journal)
A2: Worst of 3 tries. Yellow cells are inputs. Pass/Fail auto-computes where Max is numeric; qualitative rows use the PASS/FAIL dropdown.
A4: # | B4: Action | C4: Ideal (ms) | D4: Max (ms) | E4: Actual | F4: Pass/Fail | G4: Bug notes
A5: R1 | B5: Shell/skeleton visible after nav click | C5: 100 | D5: 300 | F5: =IF(E5="","",IF(E5<=D5,"PASS","FAIL"))
A6: R2 | B6: First usable content (LCP) | C6: 2000 | D6: 2500 | F6: =IF(E6="","",IF(E6<=D6,"PASS","FAIL"))
A7: R3 | B7: Data settled enough to use (1500 max allowed on heavy screens: Dashboard, Finance, Insights) | C7: 1000 | D7: 1500 | F7: =IF(E7="","",IF(E7<=D7,"PASS","FAIL"))
A8: R4 | B8: Every sub-tab: content swap | C8: 150 | D8: 250 | F8: =IF(E8="","",IF(E8<=D8,"PASS","FAIL"))
A9: R5 | B9: Every modal/sheet on this route: open | C9: 150 | D9: 250 | F9: =IF(E9="","",IF(E9<=D9,"PASS","FAIL"))
A10: R6 | B10: Every modal/sheet: close (X and Escape) | C10: 100 | D10: 200 | F10: =IF(E10="","",IF(E10<=D10,"PASS","FAIL"))
A11: R7 | B11: Every dropdown/menu/date-picker: open + selection applies | C11: 100 | D11: 200 | F11: =IF(E11="","",IF(E11<=D11,"PASS","FAIL"))
A12: R8 | B12: Search/filter input on this route: per-keystroke | C12: 50 | D12: 100 | F12: =IF(E12="","",IF(E12<=D12,"PASS","FAIL"))
A13: R9 | B13: Navigate away and back: no stale flash, state preserved | D13: —
A14: R10 | B14: Repeat primary action 5x fast: no jank, no dupes, no races | D14: —
A15: R11 | B15: CLS during load and after mutations (enter CLS value, not ms; max 0.1) | D15: 0.1 | F15: =IF(E15="","",IF(E15<=D15,"PASS","FAIL"))
A16: R12 | B16: Mobile-width rerun of R1–R11 all within limits | D16: —

Sheet Obligations
A1: Route audit — Obligations / Bills (/obligations, /bills)
A2: Worst of 3 tries. Yellow cells are inputs. Pass/Fail auto-computes where Max is numeric; qualitative rows use the PASS/FAIL dropdown.
A4: # | B4: Action | C4: Ideal (ms) | D4: Max (ms) | E4: Actual | F4: Pass/Fail | G4: Bug notes
A5: R1 | B5: Shell/skeleton visible after nav click | C5: 100 | D5: 300 | F5: =IF(E5="","",IF(E5<=D5,"PASS","FAIL"))
A6: R2 | B6: First usable content (LCP) | C6: 2000 | D6: 2500 | F6: =IF(E6="","",IF(E6<=D6,"PASS","FAIL"))
A7: R3 | B7: Data settled enough to use (1500 max allowed on heavy screens: Dashboard, Finance, Insights) | C7: 1000 | D7: 1500 | F7: =IF(E7="","",IF(E7<=D7,"PASS","FAIL"))
A8: R4 | B8: Every sub-tab: content swap | C8: 150 | D8: 250 | F8: =IF(E8="","",IF(E8<=D8,"PASS","FAIL"))
A9: R5 | B9: Every modal/sheet on this route: open | C9: 150 | D9: 250 | F9: =IF(E9="","",IF(E9<=D9,"PASS","FAIL"))
A10: R6 | B10: Every modal/sheet: close (X and Escape) | C10: 100 | D10: 200 | F10: =IF(E10="","",IF(E10<=D10,"PASS","FAIL"))
A11: R7 | B11: Every dropdown/menu/date-picker: open + selection applies | C11: 100 | D11: 200 | F11: =IF(E11="","",IF(E11<=D11,"PASS","FAIL"))
A12: R8 | B12: Search/filter input on this route: per-keystroke | C12: 50 | D12: 100 | F12: =IF(E12="","",IF(E12<=D12,"PASS","FAIL"))
A13: R9 | B13: Navigate away and back: no stale flash, state preserved | D13: —
A14: R10 | B14: Repeat primary action 5x fast: no jank, no dupes, no races | D14: —
A15: R11 | B15: CLS during load and after mutations (enter CLS value, not ms; max 0.1) | D15: 0.1 | F15: =IF(E15="","",IF(E15<=D15,"PASS","FAIL"))
A16: R12 | B16: Mobile-width rerun of R1–R11 all within limits | D16: —

Sheet Goals
A1: Route audit — Goals (/goals)
A2: Worst of 3 tries. Yellow cells are inputs. Pass/Fail auto-computes where Max is numeric; qualitative rows use the PASS/FAIL dropdown.
A4: # | B4: Action | C4: Ideal (ms) | D4: Max (ms) | E4: Actual | F4: Pass/Fail | G4: Bug notes
A5: R1 | B5: Shell/skeleton visible after nav click | C5: 100 | D5: 300 | F5: =IF(E5="","",IF(E5<=D5,"PASS","FAIL"))
A6: R2 | B6: First usable content (LCP) | C6: 2000 | D6: 2500 | F6: =IF(E6="","",IF(E6<=D6,"PASS","FAIL"))
A7: R3 | B7: Data settled enough to use (1500 max allowed on heavy screens: Dashboard, Finance, Insights) | C7: 1000 | D7: 1500 | F7: =IF(E7="","",IF(E7<=D7,"PASS","FAIL"))
A8: R4 | B8: Every sub-tab: content swap | C8: 150 | D8: 250 | F8: =IF(E8="","",IF(E8<=D8,"PASS","FAIL"))
A9: R5 | B9: Every modal/sheet on this route: open | C9: 150 | D9: 250 | F9: =IF(E9="","",IF(E9<=D9,"PASS","FAIL"))
A10: R6 | B10: Every modal/sheet: close (X and Escape) | C10: 100 | D10: 200 | F10: =IF(E10="","",IF(E10<=D10,"PASS","FAIL"))
A11: R7 | B11: Every dropdown/menu/date-picker: open + selection applies | C11: 100 | D11: 200 | F11: =IF(E11="","",IF(E11<=D11,"PASS","FAIL"))
A12: R8 | B12: Search/filter input on this route: per-keystroke | C12: 50 | D12: 100 | F12: =IF(E12="","",IF(E12<=D12,"PASS","FAIL"))
A13: R9 | B13: Navigate away and back: no stale flash, state preserved | D13: —
A14: R10 | B14: Repeat primary action 5x fast: no jank, no dupes, no races | D14: —
A15: R11 | B15: CLS during load and after mutations (enter CLS value, not ms; max 0.1) | D15: 0.1 | F15: =IF(E15="","",IF(E15<=D15,"PASS","FAIL"))
A16: R12 | B16: Mobile-width rerun of R1–R11 all within limits | D16: —

Sheet Wellness
A1: Route audit — Wellness (/wellness, /health)
A2: Worst of 3 tries. Yellow cells are inputs. Pass/Fail auto-computes where Max is numeric; qualitative rows use the PASS/FAIL dropdown.
A4: # | B4: Action | C4: Ideal (ms) | D4: Max (ms) | E4: Actual | F4: Pass/Fail | G4: Bug notes
A5: R1 | B5: Shell/skeleton visible after nav click | C5: 100 | D5: 300 | F5: =IF(E5="","",IF(E5<=D5,"PASS","FAIL"))
A6: R2 | B6: First usable content (LCP) | C6: 2000 | D6: 2500 | F6: =IF(E6="","",IF(E6<=D6,"PASS","FAIL"))
A7: R3 | B7: Data settled enough to use (1500 max allowed on heavy screens: Dashboard, Finance, Insights) | C7: 1000 | D7: 1500 | F7: =IF(E7="","",IF(E7<=D7,"PASS","FAIL"))
A8: R4 | B8: Every sub-tab: content swap | C8: 150 | D8: 250 | F8: =IF(E8="","",IF(E8<=D8,"PASS","FAIL"))
A9: R5 | B9: Every modal/sheet on this route: open | C9: 150 | D9: 250 | F9: =IF(E9="","",IF(E9<=D9,"PASS","FAIL"))
A10: R6 | B10: Every modal/sheet: close (X and Escape) | C10: 100 | D10: 200 | F10: =IF(E10="","",IF(E10<=D10,"PASS","FAIL"))
A11: R7 | B11: Every dropdown/menu/date-picker: open + selection applies | C11: 100 | D11: 200 | F11: =IF(E11="","",IF(E11<=D11,"PASS","FAIL"))
A12: R8 | B12: Search/filter input on this route: per-keystroke | C12: 50 | D12: 100 | F12: =IF(E12="","",IF(E12<=D12,"PASS","FAIL"))
A13: R9 | B13: Navigate away and back: no stale flash, state preserved | D13: —
A14: R10 | B14: Repeat primary action 5x fast: no jank, no dupes, no races | D14: —
A15: R11 | B15: CLS during load and after mutations (enter CLS value, not ms; max 0.1) | D15: 0.1 | F15: =IF(E15="","",IF(E15<=D15,"PASS","FAIL"))
A16: R12 | B16: Mobile-width rerun of R1–R11 all within limits | D16: —

Sheet Insights
A1: Route audit — Insights (/insights)
A2: Worst of 3 tries. Yellow cells are inputs. Pass/Fail auto-computes where Max is numeric; qualitative rows use the PASS/FAIL dropdown.
A4: # | B4: Action | C4: Ideal (ms) | D4: Max (ms) | E4: Actual | F4: Pass/Fail | G4: Bug notes
A5: R1 | B5: Shell/skeleton visible after nav click | C5: 100 | D5: 300 | F5: =IF(E5="","",IF(E5<=D5,"PASS","FAIL"))
A6: R2 | B6: First usable content (LCP) | C6: 2000 | D6: 2500 | F6: =IF(E6="","",IF(E6<=D6,"PASS","FAIL"))
A7: R3 | B7: Data settled enough to use (1500 max allowed on heavy screens: Dashboard, Finance, Insights) | C7: 1000 | D7: 1500 | F7: =IF(E7="","",IF(E7<=D7,"PASS","FAIL"))
A8: R4 | B8: Every sub-tab: content swap | C8: 150 | D8: 250 | F8: =IF(E8="","",IF(E8<=D8,"PASS","FAIL"))
A9: R5 | B9: Every modal/sheet on this route: open | C9: 150 | D9: 250 | F9: =IF(E9="","",IF(E9<=D9,"PASS","FAIL"))
A10: R6 | B10: Every modal/sheet: close (X and Escape) | C10: 100 | D10: 200 | F10: =IF(E10="","",IF(E10<=D10,"PASS","FAIL"))
A11: R7 | B11: Every dropdown/menu/date-picker: open + selection applies | C11: 100 | D11: 200 | F11: =IF(E11="","",IF(E11<=D11,"PASS","FAIL"))
A12: R8 | B12: Search/filter input on this route: per-keystroke | C12: 50 | D12: 100 | F12: =IF(E12="","",IF(E12<=D12,"PASS","FAIL"))
A13: R9 | B13: Navigate away and back: no stale flash, state preserved | D13: —
A14: R10 | B14: Repeat primary action 5x fast: no jank, no dupes, no races | D14: —
A15: R11 | B15: CLS during load and after mutations (enter CLS value, not ms; max 0.1) | D15: 0.1 | F15: =IF(E15="","",IF(E15<=D15,"PASS","FAIL"))
A16: R12 | B16: Mobile-width rerun of R1–R11 all within limits | D16: —

Sheet Artifacts
A1: Route audit — Artifacts / Documents (/artifacts, /documents/:id)
A2: Worst of 3 tries. Yellow cells are inputs. Pass/Fail auto-computes where Max is numeric; qualitative rows use the PASS/FAIL dropdown.
A4: # | B4: Action | C4: Ideal (ms) | D4: Max (ms) | E4: Actual | F4: Pass/Fail | G4: Bug notes
A5: R1 | B5: Shell/skeleton visible after nav click | C5: 100 | D5: 300 | F5: =IF(E5="","",IF(E5<=D5,"PASS","FAIL"))
A6: R2 | B6: First usable content (LCP) | C6: 2000 | D6: 2500 | F6: =IF(E6="","",IF(E6<=D6,"PASS","FAIL"))
A7: R3 | B7: Data settled enough to use (1500 max allowed on heavy screens: Dashboard, Finance, Insights) | C7: 1000 | D7: 1500 | F7: =IF(E7="","",IF(E7<=D7,"PASS","FAIL"))
A8: R4 | B8: Every sub-tab: content swap | C8: 150 | D8: 250 | F8: =IF(E8="","",IF(E8<=D8,"PASS","FAIL"))
A9: R5 | B9: Every modal/sheet on this route: open | C9: 150 | D9: 250 | F9: =IF(E9="","",IF(E9<=D9,"PASS","FAIL"))
A10: R6 | B10: Every modal/sheet: close (X and Escape) | C10: 100 | D10: 200 | F10: =IF(E10="","",IF(E10<=D10,"PASS","FAIL"))
A11: R7 | B11: Every dropdown/menu/date-picker: open + selection applies | C11: 100 | D11: 200 | F11: =IF(E11="","",IF(E11<=D11,"PASS","FAIL"))
A12: R8 | B12: Search/filter input on this route: per-keystroke | C12: 50 | D12: 100 | F12: =IF(E12="","",IF(E12<=D12,"PASS","FAIL"))
A13: R9 | B13: Navigate away and back: no stale flash, state preserved | D13: —
A14: R10 | B14: Repeat primary action 5x fast: no jank, no dupes, no races | D14: —
A15: R11 | B15: CLS during load and after mutations (enter CLS value, not ms; max 0.1) | D15: 0.1 | F15: =IF(E15="","",IF(E15<=D15,"PASS","FAIL"))
A16: R12 | B16: Mobile-width rerun of R1–R11 all within limits | D16: —

Sheet Editor
A1: Route audit — Editor (/editor/:id)
A2: Worst of 3 tries. Yellow cells are inputs. Pass/Fail auto-computes where Max is numeric; qualitative rows use the PASS/FAIL dropdown.
A4: # | B4: Action | C4: Ideal (ms) | D4: Max (ms) | E4: Actual | F4: Pass/Fail | G4: Bug notes
A5: R1 | B5: Shell/skeleton visible after nav click | C5: 100 | D5: 300 | F5: =IF(E5="","",IF(E5<=D5,"PASS","FAIL"))
A6: R2 | B6: First usable content (LCP) | C6: 2000 | D6: 2500 | F6: =IF(E6="","",IF(E6<=D6,"PASS","FAIL"))
A7: R3 | B7: Data settled enough to use (1500 max allowed on heavy screens: Dashboard, Finance, Insights) | C7: 1000 | D7: 1500 | F7: =IF(E7="","",IF(E7<=D7,"PASS","FAIL"))
A8: R4 | B8: Every sub-tab: content swap | C8: 150 | D8: 250 | F8: =IF(E8="","",IF(E8<=D8,"PASS","FAIL"))
A9: R5 | B9: Every modal/sheet on this route: open | C9: 150 | D9: 250 | F9: =IF(E9="","",IF(E9<=D9,"PASS","FAIL"))
A10: R6 | B10: Every modal/sheet: close (X and Escape) | C10: 100 | D10: 200 | F10: =IF(E10="","",IF(E10<=D10,"PASS","FAIL"))
A11: R7 | B11: Every dropdown/menu/date-picker: open + selection applies | C11: 100 | D11: 200 | F11: =IF(E11="","",IF(E11<=D11,"PASS","FAIL"))
A12: R8 | B12: Search/filter input on this route: per-keystroke | C12: 50 | D12: 100 | F12: =IF(E12="","",IF(E12<=D12,"PASS","FAIL"))
A13: R9 | B13: Navigate away and back: no stale flash, state preserved | D13: —
A14: R10 | B14: Repeat primary action 5x fast: no jank, no dupes, no races | D14: —
A15: R11 | B15: CLS during load and after mutations (enter CLS value, not ms; max 0.1) | D15: 0.1 | F15: =IF(E15="","",IF(E15<=D15,"PASS","FAIL"))
A16: R12 | B16: Mobile-width rerun of R1–R11 all within limits | D16: —

Sheet Settings
A1: Route audit — Settings (/settings)
A2: Worst of 3 tries. Yellow cells are inputs. Pass/Fail auto-computes where Max is numeric; qualitative rows use the PASS/FAIL dropdown.
A4: # | B4: Action | C4: Ideal (ms) | D4: Max (ms) | E4: Actual | F4: Pass/Fail | G4: Bug notes
A5: R1 | B5: Shell/skeleton visible after nav click | C5: 100 | D5: 300 | F5: =IF(E5="","",IF(E5<=D5,"PASS","FAIL"))
A6: R2 | B6: First usable content (LCP) | C6: 2000 | D6: 2500 | F6: =IF(E6="","",IF(E6<=D6,"PASS","FAIL"))
A7: R3 | B7: Data settled enough to use (1500 max allowed on heavy screens: Dashboard, Finance, Insights) | C7: 1000 | D7: 1500 | F7: =IF(E7="","",IF(E7<=D7,"PASS","FAIL"))
A8: R4 | B8: Every sub-tab: content swap | C8: 150 | D8: 250 | F8: =IF(E8="","",IF(E8<=D8,"PASS","FAIL"))
A9: R5 | B9: Every modal/sheet on this route: open | C9: 150 | D9: 250 | F9: =IF(E9="","",IF(E9<=D9,"PASS","FAIL"))
A10: R6 | B10: Every modal/sheet: close (X and Escape) | C10: 100 | D10: 200 | F10: =IF(E10="","",IF(E10<=D10,"PASS","FAIL"))
A11: R7 | B11: Every dropdown/menu/date-picker: open + selection applies | C11: 100 | D11: 200 | F11: =IF(E11="","",IF(E11<=D11,"PASS","FAIL"))
A12: R8 | B12: Search/filter input on this route: per-keystroke | C12: 50 | D12: 100 | F12: =IF(E12="","",IF(E12<=D12,"PASS","FAIL"))
A13: R9 | B13: Navigate away and back: no stale flash, state preserved | D13: —
A14: R10 | B14: Repeat primary action 5x fast: no jank, no dupes, no races | D14: —
A15: R11 | B15: CLS during load and after mutations (enter CLS value, not ms; max 0.1) | D15: 0.1 | F15: =IF(E15="","",IF(E15<=D15,"PASS","FAIL"))
A16: R12 | B16: Mobile-width rerun of R1–R11 all within limits | D16: —

Sheet CRUD
A1: CRUD diagnostic — one block per entity
A2: Open create modal 150/250 · save create feedback <100 / visible <500 · open edit 150/250 · save edit <100 / persisted <500 · delete confirm 150/250 · removal <100 / confirmed <500 · cross-page propagation <1000 / 2000 hard max. C2 failures on covered entities are P1.
A4: # | B4: Check | C4: Ideal (ms) | D4: Max (ms) | E4: Actual | F4: Pass/Fail | G4: Bug notes
A5: Task
A6: C1 | B6: Create from native UI (button feedback <100ms; visible in list) | C6: 100 | D6: 500 | F6: =IF(E6="","",IF(E6<=D6,"PASS","FAIL"))
A7: C2 | B7: Create from chat (where ai-parity-matrix says covered/added) | C7: 500 | D7: 1000 | F7: =IF(E7="","",IF(E7<=D7,"PASS","FAIL"))
A8: C3 | B8: Edit title/name (field updates immediately) | C8: 100 | D8: 500 | F8: =IF(E8="","",IF(E8<=D8,"PASS","FAIL"))
A9: C4 | B9: Edit metadata: amount, date, category, linked profile, notes | C9: 100 | D9: 500 | F9: =IF(E9="","",IF(E9<=D9,"PASS","FAIL"))
A10: C5 | B10: Delete from detail view (visual removal) | C10: 100 | D10: 500 | F10: =IF(E10="","",IF(E10<=D10,"PASS","FAIL"))
A11: C6 | B11: Delete from list/card row action (visual removal) | C11: 100 | D11: 500 | F11: =IF(E11="","",IF(E11<=D11,"PASS","FAIL"))
A12: C7 | B12: Open item from dashboard/widget | C12: 150 | D12: 300 | F12: =IF(E12="","",IF(E12<=D12,"PASS","FAIL"))
A13: C8 | B13: Open item from profile page | C13: 150 | D13: 300 | F13: =IF(E13="","",IF(E13<=D13,"PASS","FAIL"))
A14: C9 | B14: Open item from linked/related page | C14: 150 | D14: 300 | F14: =IF(E14="","",IF(E14<=D14,"PASS","FAIL"))
A15: C10 | B15: Item appears in search/filter results | D15: —
A16: C11 | B16: Item disappears everywhere after delete (lists, widgets, search, calendar) | D16: —
A17: C12 | B17: Counts, totals, badges, timeline widgets update | C17: 700 | D17: 1000 | F17: =IF(E17="","",IF(E17<=D17,"PASS","FAIL"))
A18: C13 | B18: Edit persists after navigating away and back | D18: —
A19: Habit (+ check-in)
A20: C1 | B20: Create from native UI (button feedback <100ms; visible in list) | C20: 100 | D20: 500 | F20: =IF(E20="","",IF(E20<=D20,"PASS","FAIL"))
A21: C2 | B21: Create from chat (where ai-parity-matrix says covered/added) | C21: 500 | D21: 1000 | F21: =IF(E21="","",IF(E21<=D21,"PASS","FAIL"))
A22: C3 | B22: Edit title/name (field updates immediately) | C22: 100 | D22: 500 | F22: =IF(E22="","",IF(E22<=D22,"PASS","FAIL"))
A23: C4 | B23: Edit metadata: amount, date, category, linked profile, notes | C23: 100 | D23: 500 | F23: =IF(E23="","",IF(E23<=D23,"PASS","FAIL"))
A24: C5 | B24: Delete from detail view (visual removal) | C24: 100 | D24: 500 | F24: =IF(E24="","",IF(E24<=D24,"PASS","FAIL"))
A25: C6 | B25: Delete from list/card row action (visual removal) | C25: 100 | D25: 500 | F25: =IF(E25="","",IF(E25<=D25,"PASS","FAIL"))
A26: C7 | B26: Open item from dashboard/widget | C26: 150 | D26: 300 | F26: =IF(E26="","",IF(E26<=D26,"PASS","FAIL"))
A27: C8 | B27: Open item from profile page | C27: 150 | D27: 300 | F27: =IF(E27="","",IF(E27<=D27,"PASS","FAIL"))
A28: C9 | B28: Open item from linked/related page | C28: 150 | D28: 300 | F28: =IF(E28="","",IF(E28<=D28,"PASS","FAIL"))
A29: C10 | B29: Item appears in search/filter results | D29: —
A30: C11 | B30: Item disappears everywhere after delete (lists, widgets, search, calendar) | D30: —
A31: C12 | B31: Counts, totals, badges, timeline widgets update | C31: 700 | D31: 1000 | F31: =IF(E31="","",IF(E31<=D31,"PASS","FAIL"))
A32: C13 | B32: Edit persists after navigating away and back | D32: —
A33: Expense
A34: C1 | B34: Create from native UI (button feedback <100ms; visible in list) | C34: 100 | D34: 500 | F34: =IF(E34="","",IF(E34<=D34,"PASS","FAIL"))
A35: C2 | B35: Create from chat (where ai-parity-matrix says covered/added) | C35: 500 | D35: 1000 | F35: =IF(E35="","",IF(E35<=D35,"PASS","FAIL"))
A36: C3 | B36: Edit title/name (field updates immediately) | C36: 100 | D36: 500 | F36: =IF(E36="","",IF(E36<=D36,"PASS","FAIL"))
A37: C4 | B37: Edit metadata: amount, date, category, linked profile, notes | C37: 100 | D37: 500 | F37: =IF(E37="","",IF(E37<=D37,"PASS","FAIL"))
A38: C5 | B38: Delete from detail view (visual removal) | C38: 100 | D38: 500 | F38: =IF(E38="","",IF(E38<=D38,"PASS","FAIL"))
A39: C6 | B39: Delete from list/card row action (visual removal) | C39: 100 | D39: 500 | F39: =IF(E39="","",IF(E39<=D39,"PASS","FAIL"))
A40: C7 | B40: Open item from dashboard/widget | C40: 150 | D40: 300 | F40: =IF(E40="","",IF(E40<=D40,"PASS","FAIL"))
A41: C8 | B41: Open item from profile page | C41: 150 | D41: 300 | F41: =IF(E41="","",IF(E41<=D41,"PASS","FAIL"))
A42: C9 | B42: Open item from linked/related page | C42: 150 | D42: 300 | F42: =IF(E42="","",IF(E42<=D42,"PASS","FAIL"))
A43: C10 | B43: Item appears in search/filter results | D43: —
A44: C11 | B44: Item disappears everywhere after delete (lists, widgets, search, calendar) | D44: —
A45: C12 | B45: Counts, totals, badges, timeline widgets update | C45: 700 | D45: 1000 | F45: =IF(E45="","",IF(E45<=D45,"PASS","FAIL"))
A46: C13 | B46: Edit persists after navigating away and back | D46: —
A47: Income
A48: C1 | B48: Create from native UI (button feedback <100ms; visible in list) | C48: 100 | D48: 500 | F48: =IF(E48="","",IF(E48<=D48,"PASS","FAIL"))
A49: C2 | B49: Create from chat (where ai-parity-matrix says covered/added) | C49: 500 | D49: 1000 | F49: =IF(E49="","",IF(E49<=D49,"PASS","FAIL"))
A50: C3 | B50: Edit title/name (field updates immediately) | C50: 100 | D50: 500 | F50: =IF(E50="","",IF(E50<=D50,"PASS","FAIL"))
A51: C4 | B51: Edit metadata: amount, date, category, linked profile, notes | C51: 100 | D51: 500 | F51: =IF(E51="","",IF(E51<=D51,"PASS","FAIL"))
A52: C5 | B52: Delete from detail view (visual removal) | C52: 100 | D52: 500 | F52: =IF(E52="","",IF(E52<=D52,"PASS","FAIL"))
A53: C6 | B53: Delete from list/card row action (visual removal) | C53: 100 | D53: 500 | F53: =IF(E53="","",IF(E53<=D53,"PASS","FAIL"))
A54: C7 | B54: Open item from dashboard/widget | C54: 150 | D54: 300 | F54: =IF(E54="","",IF(E54<=D54,"PASS","FAIL"))
A55: C8 | B55: Open item from profile page | C55: 150 | D55: 300 | F55: =IF(E55="","",IF(E55<=D55,"PASS","FAIL"))
A56: C9 | B56: Open item from linked/related page | C56: 150 | D56: 300 | F56: =IF(E56="","",IF(E56<=D56,"PASS","FAIL"))
A57: C10 | B57: Item appears in search/filter results | D57: —
A58: C11 | B58: Item disappears everywhere after delete (lists, widgets, search, calendar) | D58: —
A59: C12 | B59: Counts, totals, badges, timeline widgets update | C59: 700 | D59: 1000 | F59: =IF(E59="","",IF(E59<=D59,"PASS","FAIL"))
A60: C13 | B60: Edit persists after navigating away and back | D60: —
A61: Obligation (bill/subscription/payment)
A62: C1 | B62: Create from native UI (button feedback <100ms; visible in list) | C62: 100 | D62: 500 | F62: =IF(E62="","",IF(E62<=D62,"PASS","FAIL"))
A63: C2 | B63: Create from chat (where ai-parity-matrix says covered/added) | C63: 500 | D63: 1000 | F63: =IF(E63="","",IF(E63<=D63,"PASS","FAIL"))
A64: C3 | B64: Edit title/name (field updates immediately) | C64: 100 | D64: 500 | F64: =IF(E64="","",IF(E64<=D64,"PASS","FAIL"))
A65: C4 | B65: Edit metadata: amount, date, category, linked profile, notes | C65: 100 | D65: 500 | F65: =IF(E65="","",IF(E65<=D65,"PASS","FAIL"))
A66: C5 | B66: Delete from detail view (visual removal) | C66: 100 | D66: 500 | F66: =IF(E66="","",IF(E66<=D66,"PASS","FAIL"))
A67: C6 | B67: Delete from list/card row action (visual removal) | C67: 100 | D67: 500 | F67: =IF(E67="","",IF(E67<=D67,"PASS","FAIL"))
A68: C7 | B68: Open item from dashboard/widget | C68: 150 | D68: 300 | F68: =IF(E68="","",IF(E68<=D68,"PASS","FAIL"))
A69: C8 | B69: Open item from profile page | C69: 150 | D69: 300 | F69: =IF(E69="","",IF(E69<=D69,"PASS","FAIL"))
A70: C9 | B70: Open item from linked/related page | C70: 150 | D70: 300 | F70: =IF(E70="","",IF(E70<=D70,"PASS","FAIL"))
A71: C10 | B71: Item appears in search/filter results | D71: —
A72: C11 | B72: Item disappears everywhere after delete (lists, widgets, search, calendar) | D72: —
A73: C12 | B73: Counts, totals, badges, timeline widgets update | C73: 700 | D73: 1000 | F73: =IF(E73="","",IF(E73<=D73,"PASS","FAIL"))
A74: C13 | B74: Edit persists after navigating away and back | D74: —
A75: Liability
A76: C1 | B76: Create from native UI (button feedback <100ms; visible in list) | C76: 100 | D76: 500 | F76: =IF(E76="","",IF(E76<=D76,"PASS","FAIL"))
A77: C2 | B77: Create from chat (where ai-parity-matrix says covered/added) | C77: 500 | D77: 1000 | F77: =IF(E77="","",IF(E77<=D77,"PASS","FAIL"))
A78: C3 | B78: Edit title/name (field updates immediately) | C78: 100 | D78: 500 | F78: =IF(E78="","",IF(E78<=D78,"PASS","FAIL"))
A79: C4 | B79: Edit metadata: amount, date, category, linked profile, notes | C79: 100 | D79: 500 | F79: =IF(E79="","",IF(E79<=D79,"PASS","FAIL"))
A80: C5 | B80: Delete from detail view (visual removal) | C80: 100 | D80: 500 | F80: =IF(E80="","",IF(E80<=D80,"PASS","FAIL"))
A81: C6 | B81: Delete from list/card row action (visual removal) | C81: 100 | D81: 500 | F81: =IF(E81="","",IF(E81<=D81,"PASS","FAIL"))
A82: C7 | B82: Open item from dashboard/widget | C82: 150 | D82: 300 | F82: =IF(E82="","",IF(E82<=D82,"PASS","FAIL"))
A83: C8 | B83: Open item from profile page | C83: 150 | D83: 300 | F83: =IF(E83="","",IF(E83<=D83,"PASS","FAIL"))
A84: C9 | B84: Open item from linked/related page | C84: 150 | D84: 300 | F84: =IF(E84="","",IF(E84<=D84,"PASS","FAIL"))
A85: C10 | B85: Item appears in search/filter results | D85: —
A86: C11 | B86: Item disappears everywhere after delete (lists, widgets, search, calendar) | D86: —
A87: C12 | B87: Counts, totals, badges, timeline widgets update | C87: 700 | D87: 1000 | F87: =IF(E87="","",IF(E87<=D87,"PASS","FAIL"))
A88: C13 | B88: Edit persists after navigating away and back | D88: —
A89: Calendar event
A90: C1 | B90: Create from native UI (button feedback <100ms; visible in list) | C90: 100 | D90: 500 | F90: =IF(E90="","",IF(E90<=D90,"PASS","FAIL"))
A91: C2 | B91: Create from chat (where ai-parity-matrix says covered/added) | C91: 500 | D91: 1000 | F91: =IF(E91="","",IF(E91<=D91,"PASS","FAIL"))
A92: C3 | B92: Edit title/name (field updates immediately) | C92: 100 | D92: 500 | F92: =IF(E92="","",IF(E92<=D92,"PASS","FAIL"))
A93: C4 | B93: Edit metadata: amount, date, category, linked profile, notes | C93: 100 | D93: 500 | F93: =IF(E93="","",IF(E93<=D93,"PASS","FAIL"))
A94: C5 | B94: Delete from detail view (visual removal) | C94: 100 | D94: 500 | F94: =IF(E94="","",IF(E94<=D94,"PASS","FAIL"))
A95: C6 | B95: Delete from list/card row action (visual removal) | C95: 100 | D95: 500 | F95: =IF(E95="","",IF(E95<=D95,"PASS","FAIL"))
A96: C7 | B96: Open item from dashboard/widget | C96: 150 | D96: 300 | F96: =IF(E96="","",IF(E96<=D96,"PASS","FAIL"))
A97: C8 | B97: Open item from profile page | C97: 150 | D97: 300 | F97: =IF(E97="","",IF(E97<=D97,"PASS","FAIL"))
A98: C9 | B98: Open item from linked/related page | C98: 150 | D98: 300 | F98: =IF(E98="","",IF(E98<=D98,"PASS","FAIL"))
A99: C10 | B99: Item appears in search/filter results | D99: —
A100: C11 | B100: Item disappears everywhere after delete (lists, widgets, search, calendar) | D100: —
A101: C12 | B101: Counts, totals, badges, timeline widgets update | C101: 700 | D101: 1000 | F101: =IF(E101="","",IF(E101<=D101,"PASS","FAIL"))
...

Sheet Chat Diagnostic
A1: Chat diagnostic — stricter limits: chat is the primary surface
A3: # | B3: Action | C3: Ideal (ms) | D3: Max (ms) | E3: Actual | F3: Pass/Fail | G3: Bug notes
A4: CH1 | B4: Focus composer | C4: 50 | D4: 100 | F4: =IF(E4="","",IF(E4<=D4,"PASS","FAIL"))
A5: CH2 | B5: Typing latency (16ms/frame budget) | C5: 16 | D5: 100 | F5: =IF(E5="","",IF(E5<=D5,"PASS","FAIL"))
A6: CH3 | B6: Suggested prompt chip inserts text | C6: 50 | D6: 100 | F6: =IF(E6="","",IF(E6<=D6,"PASS","FAIL"))
A7: CH4 | B7: Attachment picker opens | C7: 150 | D7: 250 | F7: =IF(E7="","",IF(E7<=D7,"PASS","FAIL"))
A8: CH5 | B8: Send button reacts | C8: 50 | D8: 100 | F8: =IF(E8="","",IF(E8<=D8,"PASS","FAIL"))
A9: CH6 | B9: User bubble appears (before server completes) | C9: 50 | D9: 100 | F9: =IF(E9="","",IF(E9<=D9,"PASS","FAIL"))
A10: CH7 | B10: Assistant 'thinking' state visible | C10: 100 | D10: 200 | F10: =IF(E10="","",IF(E10<=D10,"PASS","FAIL"))
A11: CH8 | B11: Tool-result cards / extracted records render progressively, non-blocking | D11: —
A12: CH9 | B12: Chat thread open | C12: 300 | D12: 700 | F12: =IF(E12="","",IF(E12<=D12,"PASS","FAIL"))
A13: CH10 | B13: Chat-created item appears in its module without refresh | C13: 500 | D13: 1000 | F13: =IF(E13="","",IF(E13<=D13,"PASS","FAIL"))
A14: CH11 | B14: Return to chat: thread restored from cache, no full reload | C14: 300 | D14: 700 | F14: =IF(E14="","",IF(E14<=D14,"PASS","FAIL"))
A15: CH12 | B15: Bulk 'here's my day' multi-action message: all records land, UI responsive | D15: —

Sheet Navigation
A1: Navigation diagnostic — every transition has its own SLA
A3: # | B3: Action | C3: Ideal (ms) | D3: Max (ms) | E3: Actual | F3: Pass/Fail | G3: Bug notes
A4: N1 | B4: Main nav (sidebar/hub tab) click — visual response | C4: 50 | D4: 100 | F4: =IF(E4="","",IF(E4<=D4,"PASS","FAIL"))
A5: N2 | B5: Route shell visible | C5: 150 | D5: 300 | F5: =IF(E5="","",IF(E5<=D5,"PASS","FAIL"))
A6: N3 | B6: Route data settled (normal screen) | C6: 700 | D6: 1000 | F6: =IF(E6="","",IF(E6<=D6,"PASS","FAIL"))
A7: N4 | B7: Route data settled (heavy: dashboard, finance, insights) | C7: 1000 | D7: 1500 | F7: =IF(E7="","",IF(E7<=D7,"PASS","FAIL"))
A8: N5 | B8: Sub-tab switch incl. query-param tabs (/linked?tab=assets) | C8: 150 | D8: 250 | F8: =IF(E8="","",IF(E8<=D8,"PASS","FAIL"))
A9: N6 | B9: Profile-to-profile switch — zero data from previous profile visible | C9: 150 | D9: 250 | F9: =IF(E9="","",IF(E9<=D9,"PASS","FAIL"))
A10: N7 | B10: Open linked entity from a card | C10: 150 | D10: 300 | F10: =IF(E10="","",IF(E10<=D10,"PASS","FAIL"))
A11: N8 | B11: Back from detail page — list state + scroll preserved | C11: 100 | D11: 250 | F11: =IF(E11="","",IF(E11<=D11,"PASS","FAIL"))
A12: N9 | B12: Open settings / notifications / avatar menu | C12: 100 | D12: 250 | F12: =IF(E12="","",IF(E12<=D12,"PASS","FAIL"))
A13: N10 | B13: Open + close drawers, overlays, full-screen dialogs (animation complete) | C13: 150 | D13: 250 | F13: =IF(E13="","",IF(E13<=D13,"PASS","FAIL"))
A14: N11 | B14: Legacy aliases resolve, no 404/double-render (/bills, /health, /profile/:id, /dashboard/*) | D14: —
A15: N12 | B15: Query-string deep links match (/tasks?new=1, /finance?new=expense) | D15: —

Sheet Micro
A1: Pop-ups and microinteractions — INP-aligned rubric
A2: <100ms excellent · 100–200 acceptable · 200–300 noticeable lag (P2) · >300 FAIL. Rating auto-computes from Actual.
A4: # | B4: Microinteraction | C4: Actual (ms) | D4: Rating | E4: Pass/Fail | F4: Bug notes
A5: M1 | B5: Tooltip opens | D5: =IF(C5="","",IF(C5<100,"Excellent",IF(C5<=200,"Acceptable",IF(C5<=300,"Noticeable lag (P2)","FAIL")))) | E5: =IF(C5="","",IF(C5<=300,"PASS","FAIL"))
A6: M2 | B6: Dropdown opens | D6: =IF(C6="","",IF(C6<100,"Excellent",IF(C6<=200,"Acceptable",IF(C6<=300,"Noticeable lag (P2)","FAIL")))) | E6: =IF(C6="","",IF(C6<=300,"PASS","FAIL"))
A7: M3 | B7: Dropdown selection applies | D7: =IF(C7="","",IF(C7<100,"Excellent",IF(C7<=200,"Acceptable",IF(C7<=300,"Noticeable lag (P2)","FAIL")))) | E7: =IF(C7="","",IF(C7<=300,"PASS","FAIL"))
A8: M4 | B8: Context menu opens | D8: =IF(C8="","",IF(C8<100,"Excellent",IF(C8<=200,"Acceptable",IF(C8<=300,"Noticeable lag (P2)","FAIL")))) | E8: =IF(C8="","",IF(C8<=300,"PASS","FAIL"))
A9: M5 | B9: Avatar menu opens | D9: =IF(C9="","",IF(C9<100,"Excellent",IF(C9<=200,"Acceptable",IF(C9<=300,"Noticeable lag (P2)","FAIL")))) | E9: =IF(C9="","",IF(C9<=300,"PASS","FAIL"))
A10: M6 | B10: Confirmation modal opens | D10: =IF(C10="","",IF(C10<100,"Excellent",IF(C10<=200,"Acceptable",IF(C10<=300,"Noticeable lag (P2)","FAIL")))) | E10: =IF(C10="","",IF(C10<=300,"PASS","FAIL"))
A11: M7 | B11: Sheet/drawer opens | D11: =IF(C11="","",IF(C11<100,"Excellent",IF(C11<=200,"Acceptable",IF(C11<=300,"Noticeable lag (P2)","FAIL")))) | E11: =IF(C11="","",IF(C11<=300,"PASS","FAIL"))
A12: M8 | B12: Date picker opens | D12: =IF(C12="","",IF(C12<100,"Excellent",IF(C12<=200,"Acceptable",IF(C12<=300,"Noticeable lag (P2)","FAIL")))) | E12: =IF(C12="","",IF(C12<=300,"PASS","FAIL"))
A13: M9 | B13: Quick-create FAB menu opens | D13: =IF(C13="","",IF(C13<100,"Excellent",IF(C13<=200,"Acceptable",IF(C13<=300,"Noticeable lag (P2)","FAIL")))) | E13: =IF(C13="","",IF(C13<=300,"PASS","FAIL"))
A14: M10 | B14: Chat suggestion bubble inserts text | D14: =IF(C14="","",IF(C14<100,"Excellent",IF(C14<=200,"Acceptable",IF(C14<=300,"Noticeable lag (P2)","FAIL")))) | E14: =IF(C14="","",IF(C14<=300,"PASS","FAIL"))
A15: M11 | B15: Toast appears after save/delete | D15: =IF(C15="","",IF(C15<100,"Excellent",IF(C15<=200,"Acceptable",IF(C15<=300,"Noticeable lag (P2)","FAIL")))) | E15: =IF(C15="","",IF(C15<=300,"PASS","FAIL"))
A16: M12 | B16: Close icon works instantly | D16: =IF(C16="","",IF(C16<100,"Excellent",IF(C16<=200,"Acceptable",IF(C16<=300,"Noticeable lag (P2)","FAIL")))) | E16: =IF(C16="","",IF(C16<=300,"PASS","FAIL"))
A17: M13 | B17: Escape key closes overlays instantly | D17: =IF(C17="","",IF(C17<100,"Excellent",IF(C17<=200,"Acceptable",IF(C17<=300,"Noticeable lag (P2)","FAIL")))) | E17: =IF(C17="","",IF(C17<=300,"PASS","FAIL"))

Sheet Sync
A1: Dashboard and sync diagnostic — run after ANY mutation
A3: # | B3: Action | C3: Ideal (ms) | D3: Max (ms) | E3: Actual | F3: Pass/Fail | G3: Bug notes
A4: S1 | B4: Same-screen optimistic update | D4: 100 | F4: =IF(E4="","",IF(E4<=D4,"PASS","FAIL"))
A5: S2 | B5: Same-screen server-confirmed state | D5: 500 | F5: =IF(E5="","",IF(E5<=D5,"PASS","FAIL"))
A6: S3 | B6: Related widgets on same route | D6: 700 | F6: =IF(E6="","",IF(E6<=D6,"PASS","FAIL"))
A7: S4 | B7: Other cached routes invalidated/refreshed | D7: 1000 | F7: =IF(E7="","",IF(E7<=D7,"PASS","FAIL"))
A8: S5 | B8: Dashboard aggregate recompute visible (counts, totals, net worth) | D8: 1000 | F8: =IF(E8="","",IF(E8<=D8,"PASS","FAIL"))
A9: S6 | B9: Full system consistency after mutation | D9: 2000 | F9: =IF(E9="","",IF(E9<=D9,"PASS","FAIL"))
A11: Functional checks after each mutation (YES = verified OK, NO = defect):
B12: Dashboard counts update
B13: Progress rings/bars update (habits, goals, budgets)
B14: Profile counters update
B15: Calendar shows/removes date-based items (events, tasks, obligations, habit check-ins)
B16: Money totals update for finance mutations (expenses, income, obligations, liabilities, net worth)
B17: Linked assets/relationships refresh correctly
B18: Search results reflect latest state
B19: Filters show no ghost records
B20: Deleted records gone from every cached list
B21: Returning to same route: no stale-value flash
B22: Mutation scoped to correct profile — zero cross-profile leakage
